{
    "version": "2.2.3",
    "description": "Nacos: Dynamic Naming and Configuration Service",
    "homepage": "https://github.com/alibaba/nacos",
    "license": "Apache-2.0",
    "architecture": {
        "64bit": {
            "url": "https://github.com/alibaba/nacos/releases/download/2.2.3/nacos-server-2.2.3.zip",
            "hash": "d4199f5ce28fb93b5b16aff6bf65367e64c0f7e668b9d8dd8048ea97db4cf867"
        }
    },
    "bin": [
        [
            "nacos\\bin\\startup.cmd",
            "nacos-startup"
        ]
    ],
    "checkver": "github",
    "autoupdate": {
        "architecture": {
            "64bit": {
                "url": "https://github.com/alibaba/nacos/releases/download/$version/nacos-server-$version.zip"
            }
        }
    }
}
