{
    "version": "2.2.0",
    "description": "Nacos: Dynamic Naming and Configuration Service",
    "homepage": "https://github.com/alibaba/nacos",
    "license": "Apache-2.0",
    "architecture": {
        "64bit": {
            "url": "https://github.com/alibaba/nacos/releases/download/2.2.0/nacos-server-2.2.0.zip",
            "hash": "faf4e405838545d00f7d7bd10438f6ceb4a798fe0ad071d9e76fc8daf29bb0c5"
        }
    },
    "bin": [
        [
            "nacos\\bin\\startup.cmd",
            "nacos-startup"
        ]
    ],
    "checkver": "github",
    "autoupdate": {
        "architecture": {
            "64bit": {
                "url": "https://github.com/alibaba/nacos/releases/download/$version/nacos-server-$version.zip"
            }
        }
    }
}
